setup.cfg
setup.py
spotify/__init__.py
spotify/http.py
spotify/page.py
spotify/resource.py
spotify/values.py
spotify/auth/__init__.py
spotify/auth/client.py
spotify/auth/scope.py
spotify/auth/user.py
spotify/auth/util.py
spotify/object/__init__.py
spotify/object/audio_analysis.py
spotify/object/context.py
spotify/object/copyright.py
spotify/object/device.py
spotify/object/followers.py
spotify/object/image.py
spotify/object/seed.py
spotify/object/snapshot.py
spotify/v1/__init__.py
spotify/v1/audio_analysis.py
spotify/v1/audio_features.py
spotify/v1/search.py
spotify/v1/track.py
spotify/v1/album/__init__.py
spotify/v1/album/track.py
spotify/v1/artist/__init__.py
spotify/v1/artist/album.py
spotify/v1/artist/related_artist.py
spotify/v1/artist/top_track.py
spotify/v1/browse/__init__.py
spotify/v1/browse/featured_playlist.py
spotify/v1/browse/new_release.py
spotify/v1/browse/categories/__init__.py
spotify/v1/browse/categories/playlist.py
spotify/v1/me/__init__.py
spotify/v1/me/album.py
spotify/v1/me/following.py
spotify/v1/me/playlist.py
spotify/v1/me/track.py
spotify/v1/me/player/__init__.py
spotify/v1/me/player/currently_playing.py
spotify/v1/me/player/device.py
spotify/v1/me/player/recently_played.py
spotify/v1/me/top/__init__.py
spotify/v1/me/top/artist.py
spotify/v1/me/top/track.py
spotify/v1/recommendation/__init__.py
spotify/v1/recommendation/available_genre_seeds.py
spotify/v1/user/__init__.py
spotify/v1/user/playlist/__init__.py
spotify/v1/user/playlist/follower.py
spotify/v1/user/playlist/image.py
spotify/v1/user/playlist/track.py
spotify_python.egg-info/PKG-INFO
spotify_python.egg-info/SOURCES.txt
spotify_python.egg-info/dependency_links.txt
spotify_python.egg-info/requires.txt
spotify_python.egg-info/top_level.txt