Metadata-Version: 1.0
Name: spotify-python
Version: 0.0.1
Summary: Python Library for Spotify Web API
Home-page: https://github.com/jingming/spotify/
Author: Jingming Niu
Author-email: niu@jingming.ca
License: UNKNOWN
Keywords: spotify,music
Platform: UNKNOWN
